dandeliion/client/#simulator.py#
dandeliion/client/__init__.py
dandeliion/client/exceptions.py
dandeliion/client/experiment.py
dandeliion/client/simulator.py
dandeliion/client/simulator.py.new
dandeliion/client/solution.py
dandeliion/client/websocket.py
dandeliion/client/websocket.py.new
dandeliion/client/tools/misc.py
dandeliion_client-1.1.0.dist-info/METADATA
dandeliion_client-1.1.0.dist-info/WHEEL
dandeliion_client-1.1.0.dist-info/licenses/LICENSE
dandeliion_client-1.1.0.dist-info/RECORD
