Metadata-Version: 2.4
Name: dandeliion-client
Version: 1.1.0
Summary: Client for accessing Dandeliion services
Project-URL: Homepage, https://dandeliion.com
Project-URL: Documentation, https://dandeliion-team.github.io/dandeliion-client/
Project-URL: Repository, https://github.com/dandeliion-team/dandeliion-client
Project-URL: Bug Tracker, https://github.com/dandeliion-team/dandeliion-client/issues
Project-URL: Changelog, https://github.com/dandeliion-team/dandeliion-client/blob/develop/CHANGELOG.md
Author-email: DandeLiion Team <team@dandeliion.com>
Maintainer-email: DandeLiion Team <team@dandeliion.com>
License: Copyright (c) 2025, DandeLiion Team
License-File: LICENSE
Keywords: client,dandeliion
Classifier: Development Status :: 5 - Production/Stable
Classifier: Intended Audience :: Science/Research
Classifier: Programming Language :: Python
Requires-Python: >=3.9
Requires-Dist: bpx
Requires-Dist: python-socketio~=5.13.0
Requires-Dist: requests~=2.32.3
Requires-Dist: websocket-client~=1.8.0
Provides-Extra: dev
Requires-Dist: black; extra == 'dev'
Requires-Dist: flake8; extra == 'dev'
Requires-Dist: flake8-docstrings; extra == 'dev'
Requires-Dist: mypy; extra == 'dev'
Requires-Dist: nox; extra == 'dev'
Requires-Dist: pre-commit; extra == 'dev'
Requires-Dist: pybamm~=25.6.0; extra == 'dev'
Requires-Dist: pytest; extra == 'dev'
Requires-Dist: pytest-cov; extra == 'dev'
Requires-Dist: pytest-sugar; extra == 'dev'
Requires-Dist: pytest-timeout; extra == 'dev'
Provides-Extra: docs
Requires-Dist: ipykernel; extra == 'docs'
Requires-Dist: ipywidgets; extra == 'docs'
Requires-Dist: myst-parser; extra == 'docs'
Requires-Dist: nbsphinx; extra == 'docs'
Requires-Dist: pybamm~=25.6.0; extra == 'docs'
Requires-Dist: pydata-sphinx-theme; extra == 'docs'
Requires-Dist: sphinx-autobuild; extra == 'docs'
Requires-Dist: sphinx-copybutton; extra == 'docs'
Requires-Dist: sphinx-design; extra == 'docs'
Requires-Dist: sphinx-docsearch; extra == 'docs'
Requires-Dist: sphinx-gallery; extra == 'docs'
Requires-Dist: sphinx-hoverxref; extra == 'docs'
Requires-Dist: sphinx-inline-tabs; extra == 'docs'
Requires-Dist: sphinx-last-updated-by-git; extra == 'docs'
Requires-Dist: sphinx-rtd-theme>=0.5; extra == 'docs'
Requires-Dist: sphinx>=6; extra == 'docs'
Requires-Dist: sphinxcontrib-bibtex; extra == 'docs'
Provides-Extra: pybamm
Requires-Dist: pybamm~=25.6.0; extra == 'pybamm'
